aery/__init__.py
aery-0.1.0.dist-info/LICENSE
aery-0.1.0.dist-info/METADATA
aery-0.1.0.dist-info/WHEEL
aery-0.1.0.dist-info/top_level.txt
aery-0.1.0.dist-info/RECORD
