Metadata-Version: 2.1
Name: aery
Version: 0.1.0
Summary: AeryAI.com
Author: Evan Raw
Author-email: evanraw.ca@gmail.com
License: MIT
License-File: LICENSE
